MANIFEST.in
README.rst
setup.py
pseudomyth/__init__.py
pseudomyth.egg-info/PKG-INFO
pseudomyth.egg-info/SOURCES.txt
pseudomyth.egg-info/dependency_links.txt
pseudomyth.egg-info/top_level.txt
scripts/pseudomyth