Metadata-Version: 1.1
Name: pseudomyth
Version: 1.0.7
Summary: A script with which to determine what order to watch anime episodes in
Home-page: https://github.com/colons/pseudomyth
Author: Iain Dawson
Author-email: pypi@colons.co
License: BSD
Platform: any
Classifier: License :: OSI Approved :: BSD License
Classifier: Operating System :: OS Independent
